modal/__init__.py
modal/__main__.py
modal/_clustered_functions.py
modal/_container_entrypoint.py
modal/_functions.py
modal/_ipython.py
modal/_location.py
modal/_object.py
modal/_output.py
modal/_partial_function.py
modal/_pty.py
modal/_resolver.py
modal/_resources.py
modal/_serialization.py
modal/_traceback.py
modal/_tunnel.py
modal/_type_manager.py
modal/_watcher.py
modal/app.py
modal/call_graph.py
modal/client.py
modal/cloud_bucket_mount.py
modal/cls.py
modal/config.py
modal/container_process.py
modal/dict.py
modal/environments.py
modal/exception.py
modal/file_io.py
modal/file_pattern_matcher.py
modal/functions.py
modal/gpu.py
modal/image.py
modal/io_streams.py
modal/mount.py
modal/network_file_system.py
modal/object.py
modal/output.py
modal/parallel_map.py
modal/partial_function.py
modal/proxy.py
modal/py.typed
modal/queue.py
modal/retries.py
modal/runner.py
modal/running_app.py
modal/sandbox.py
modal/schedule.py
modal/scheduler_placement.py
modal/secret.py
modal/serving.py
modal/snapshot.py
modal/stream_type.py
modal/token_flow.py
modal/volume.py
modal/_runtime/__init__.py
modal/_runtime/asgi.py
modal/_runtime/container_io_manager.py
modal/_runtime/execution_context.py
modal/_runtime/gpu_memory_snapshot.py
modal/_runtime/telemetry.py
modal/_runtime/user_code_imports.py
modal/_utils/__init__.py
modal/_utils/app_utils.py
modal/_utils/async_utils.py
modal/_utils/auth_token_manager.py
modal/_utils/blob_utils.py
modal/_utils/bytes_io_segment_payload.py
modal/_utils/deprecation.py
modal/_utils/docker_utils.py
modal/_utils/function_utils.py
modal/_utils/git_utils.py
modal/_utils/grpc_testing.py
modal/_utils/grpc_utils.py
modal/_utils/hash_utils.py
modal/_utils/http_utils.py
modal/_utils/jwt_utils.py
modal/_utils/logger.py
modal/_utils/mount_utils.py
modal/_utils/name_utils.py
modal/_utils/package_utils.py
modal/_utils/pattern_utils.py
modal/_utils/rand_pb_testing.py
modal/_utils/shell_utils.py
modal/_utils/time_utils.py
modal/_vendor/__init__.py
rfmodal-1.2.6.dist-info/licenses/LICENSE
rfmodal-1.2.6.dist-info/METADATA
rfmodal-1.2.6.dist-info/WHEEL
rfmodal-1.2.6.dist-info/entry_points.txt
rfmodal-1.2.6.dist-info/top_level.txt
rfmodal-1.2.6.dist-info/RECORD
