Metadata-Version: 2.4
Name: rfmodal
Version: 1.2.6
Summary: Roboflow fork of Modal Python client library
Author-email: Modal Labs <support@modal.com>
License: Apache-2.0
Project-URL: Homepage, https://modal.com
Project-URL: Source, https://github.com/modal-labs/modal-client
Project-URL: Documentation, https://modal.com/docs
Project-URL: Issue Tracker, https://github.com/modal-labs/modal-client/issues
Keywords: modal,client,cloud,serverless,infrastructure
Classifier: Topic :: System :: Distributed Computing
Classifier: Operating System :: OS Independent
Classifier: License :: OSI Approved :: Apache Software License
Classifier: Programming Language :: Python :: 3
Requires-Python: >=3.9
License-File: LICENSE
Requires-Dist: aiohttp
Requires-Dist: certifi
Requires-Dist: click~=8.1
Requires-Dist: grpclib<0.4.9,>=0.4.7
Requires-Dist: protobuf!=4.24.0,<7.0,>=3.19
Requires-Dist: rffickle
Requires-Dist: rich>=12.0.0
Requires-Dist: synchronicity~=0.10.2
Requires-Dist: toml
Requires-Dist: typer>=0.9
Requires-Dist: types-certifi
Requires-Dist: types-toml
Requires-Dist: watchfiles
Requires-Dist: typing_extensions~=4.6
Dynamic: license-file
